hand_tracker/__init__.py
hand_tracker/detector.py
hand_tracker/assets/Configurations/calibration.yaml
hand_tracker/assets/Configurations/config.yaml
hand_tracker/assets/Configurations/gestures.yaml
hand_tracker/assets/Models/hand_landmarker.task
mtc_handtracker-1.0.1.dist-info/licenses/LICENSE
mtc_handtracker-1.0.1.dist-info/METADATA
mtc_handtracker-1.0.1.dist-info/WHEEL
mtc_handtracker-1.0.1.dist-info/top_level.txt
mtc_handtracker-1.0.1.dist-info/RECORD
