Metadata-Version: 2.4
Name: MTC-HandTracker
Version: 1.0.1
Summary: A professional, modular hand tracking library for robotics.
Home-page: https://github.com/McMaster-Technology-Club/Hand-Tracking
Author: Majd Aburas (McMaster Technology Club)
Author-email: aburasm@mcmaster.ca
Classifier: Programming Language :: Python :: 3
Classifier: License :: OSI Approved :: GNU Affero General Public License v3 or later (AGPLv3+)
Classifier: Operating System :: OS Independent
Classifier: Topic :: Scientific/Engineering :: Image Recognition
Classifier: Topic :: Software Development :: Libraries :: Python Modules
Requires-Python: >=3.8, <3.13
License-File: LICENSE
Requires-Dist: opencv-python
Requires-Dist: mediapipe
Requires-Dist: numpy
Requires-Dist: pyyaml
Dynamic: author
Dynamic: author-email
Dynamic: classifier
Dynamic: description
Dynamic: description-content-type
Dynamic: home-page
Dynamic: license-file
Dynamic: requires-dist
Dynamic: requires-python
Dynamic: summary
